rangealert/__init__.py
rangealert/example.py
rangealert/ralert.py
rangealert-0.0.1.dist-info/LICENSE.txt
rangealert-0.0.1.dist-info/METADATA
rangealert-0.0.1.dist-info/WHEEL
rangealert-0.0.1.dist-info/top_level.txt
rangealert-0.0.1.dist-info/RECORD
