Metadata-Version: 2.1
Name: rangealert
Version: 0.0.1
Summary: Range bound trading screener
Home-page: https://github.com/jonleonATX/range_trading_alert
Author: Jonathan Leon
Author-email: jonleonaustin@gmail.com
License: UNKNOWN
Platform: UNKNOWN
Classifier: Programming Language :: Python :: 3
Classifier: License :: OSI Approved :: MIT License
Classifier: Operating System :: OS Independent
Requires-Python: >=3.6
